Workbook

Sheet 1 收入测算
A1: 收入来源 | B1: Q1 | C1: Q2 | D1: Q3 | E1: Q4 | F1: 全年 | G1: 计算依据 | H1: 口径与假设
A2: 礼物与付费留言净到账 | B2: 1200 | C2: 3000 | D2: 5300 | E2: 7900 | F2: =SUM(B2:E2) | G2: 计划书季度目标值；计划书给出的方法为“有效观众×实际付费比例×人均净收入”，但未给出各参数取值 | H2: 净到账＝扣除平台分成后；税费未单列（假设）
A3: 会员净到账 | B3: 0 | C3: 0 | D3: =B10*B11 | E3: =B14*B11 | F3: =SUM(B3:E3) | G3: 会员月 × 每会员月净到账 | H3: 50 元/会员月为情景假设，不是平台定价；会员自 Q3 起
A4: 周边销售 | B4: 0 | C4: 0 | D4: 5000 | E4: 10000 | F4: =SUM(B4:E4) | G4: 计划书目标销售额；款式、单价、销量未给出 | H4: 预售回款；履约成本见支出表
A5: 商业合作收款 | B5: 0 | C5: 0 | D5: 0 | E5: =B12*B13 | F5: =SUM(B5:E5) | G5: 合作次数 × 每次收款 | H5: 首年两次、每次 5,000 元为目标，以签约结算为准
A6: 收入合计 | B6: =SUM(B2:B5) | C6: =SUM(C2:C5) | D6: =SUM(D2:D5) | E6: =SUM(E2:E5) | F6: =SUM(F2:F5)
A9: 参数 | B9: 值 | G9: 说明
A10: Q3 会员月 | B10: 105 | G10: 5,250 ÷ 50
A11: 每会员月净到账（元） | B11: 50 | G11: 情景假设
A12: 合作次数（Q4） | B12: 2 | G12: 目标
A13: 每次合作收款（元） | B13: 5000 | G13: 目标
A14: Q4 会员月 | B14: 280 | G14: 14,000 ÷ 50；全年 105＋280＝385 会员月

Sheet 2 支出测算
A1: 支出项目 | B1: 全年 | C1: 每季度 | D1: 频次/口径 | E1: 备注
A2: 模型语音云服务 | B2: 18000 | C2: =B2/4 | D2: 约 1,500 元/月 | E2: 日常运营
A3: 剪辑与社群补贴 | B3: 12000 | C3: =B3/4 | D3: 约 1,000 元/月 | E3: 日常运营
A4: 推广 | B4: 18000 | C4: =B4/4 | D4: 分批投放 | E4: 日常运营；先比较自然流量，再追加
A5: 活动杂费 | B5: 4000 | C5: =B5/4 | D5: 约 333 元/月 | E5: 日常运营
A6: 日常运营小计 | B6: =SUM(B2:B5) | C6: =SUM(C2:C5) | E6: 计划书：52,000 元
A7: 周边制作履约 | B7: 10500 | D7: Q3 3,500；Q4 7,000 | E7: 为周边销售额的 70%
A8: 运营与履约现金支出合计 | B8: =B6+B7 | E8: 计划书：62,500 元
A10: 启动投入（单列，不计入日常运营）
A11: 原画 | B11: 8000 | D11: 一次性 | E11: 11 月底交付；尚未付款（用户确认）
A12: Live2D 及表情 | B12: 14000 | D12: 一次性 | E12: 11 月底交付；尚未付款（用户确认）
A13: 开发工具 | B13: 3000 | D13: 一次性
A14: 启动投入小计 | B14: =SUM(B11:B13) | E14: 计划书：25,000 元
A16: 团队成员薪酬 | B16: 0 | E16: 团队成员不领薪（用户确认）；工时另行登记，不进现金预算

Sheet 3 现金流
A1: 期间 | B1: 收入 | C1: 日常运营 | D1: 周边履约 | E1: 启动投入 | F1: 当期净现金 | G1: 累计现金（含启动） | H1: 说明
A2: 期初 | B2: 0 | C2: 0 | D2: 0 | E2: 25000 | F2: =B2-C2-D2-E2 | G2: =F2
A3: Q1 | B3: ='1 收入测算'!B6 | C3: 13000 | D3: 0 | E3: 0 | F3: =B3-C3-D3-E3 | G3: =G2+F3
A4: Q2 | B4: ='1 收入测算'!C6 | C4: 13000 | D4: 0 | E4: 0 | F4: =B4-C4-D4-E4 | G4: =G3+F4
A5: Q3 | B5: ='1 收入测算'!D6 | C5: 13000 | D5: 3500 | E5: 0 | F5: =B5-C5-D5-E5 | G5: =G4+F5
A6: Q4 | B6: ='1 收入测算'!E6 | C6: 13000 | D6: 7000 | E6: 0 | F6: =B6-C6-D6-E6 | G6: =G5+F6
A7: 全年合计 | B7: =SUM(B3:B6) | C7: =SUM(C3:C6) | D7: =SUM(D3:D6) | E7: =E2 | F7: =SUM(F2:F6) | H7: 含启动的全年现金缺口
A9: 月度（按季度平均分摊） | F9: 当月净现金 | G9: 累计现金
A10: 第 1 月 | B10: =B3/3 | C10: =C3/3 | D10: =D3/3 | F10: =B10-C10-D10 | G10: =-E2+F10
A11: 第 2 月 | B11: =B3/3 | C11: =C3/3 | D11: =D3/3 | F11: =B11-C11-D11 | G11: =G10+F11
A12: 第 3 月 | B12: =B3/3 | C12: =C3/3 | D12: =D3/3 | F12: =B12-C12-D12 | G12: =G11+F12
A13: 第 4 月 | B13: =B4/3 | C13: =C4/3 | D13: =D4/3 | F13: =B13-C13-D13 | G13: =G12+F13
A14: 第 5 月 | B14: =B4/3 | C14: =C4/3 | D14: =D4/3 | F14: =B14-C14-D14 | G14: =G13+F14
A15: 第 6 月 | B15: =B4/3 | C15: =C4/3 | D15: =D4/3 | F15: =B15-C15-D15 | G15: =G14+F15
A16: 第 7 月 | B16: =B5/3 | C16: =C5/3 | D16: =D5/3 | F16: =B16-C16-D16 | G16: =G15+F16
A17: 第 8 月 | B17: =B5/3 | C17: =C5/3 | D17: =D5/3 | F17: =B17-C17-D17 | G17: =G16+F17
A18: 第 9 月 | B18: =B5/3 | C18: =C5/3 | D18: =D5/3 | F18: =B18-C18-D18 | G18: =G17+F18
A19: 第 10 月 | B19: =B6/3 | C19: =C6/3 | D19: =D6/3 | F19: =B19-C19-D19 | G19: =G18+F19
A20: 第 11 月 | B20: =B6/3 | C20: =C6/3 | D20: =D6/3 | F20: =B20-C20-D20 | G20: =G19+F20
A21: 第 12 月 | B21: =B6/3 | C21: =C6/3 | D21: =D6/3 | F21: =B21-C21-D21 | G21: =G20+F21
A22: 累计现金最低点（最高垫付） | G22: =MIN(G10:G21) | H22: 原稿约 47,750 元；平均分摊下出现在第 9 月末

Sheet 4 指标
A1: 指标 | B1: 分子 | C1: 分母 | D1: 结果 | E1: 说明
A2: 运营履约覆盖率 | B2: ='1 收入测算'!F6 | C2: ='2 支出测算'!B8 | D2: =B2/C2 | E2: 年收入 ÷（日常运营＋周边履约）；低于 100% 表示尚未覆盖
A3: 含启动投入覆盖率 | B3: ='1 收入测算'!F6 | C3: ='2 支出测算'!B8+'2 支出测算'!B14 | D3: =B3/C3 | E3: 年收入 ÷（运营履约＋启动投入）
A4: 运营现金差额（元） | B4: ='1 收入测算'!F6 | C4: ='2 支出测算'!B8 | D4: =B4-C4 | E4: 原稿：负 850 元
A5: 含启动全年现金缺口（元） | D5: =D4-'2 支出测算'!B14 | E5: 原稿：负 25,850 元
A6: 累计最高垫付（元） | D6: ='3 现金流'!G22 | E6: 原稿：约 47,750 元；不等于年末缺口
A7: 保守情景缺口（元） | B7: 8000 | C7: =40000+25000 | D7: =B7-C7 | E7: 计划书：会员与合作延后，打赏 8,000、日常 40,000、启动 25,000，缺口约 57,000

Sheet 5 申请额重算
A1: 项目 | B1: 原稿 10 万方案 | C1: 首阶段推荐（1–6 月） | D1: 取舍说明
A2: 原画 | B2: 8000 | C2: 8000 | D2: 必要：原创形象首版，11 月底交付
A3: Live2D 及表情 | B3: 14000 | C3: 14000 | D3: 必要：直播形象
A4: 开发工具 | B4: 3000 | C4: 3000 | D4: 必要
A5: 模型语音云服务 | B5: 18000 | C5: 9000 | D5: 按 1,500 元/月 × 6 月，全额保留
A6: 剪辑与社群补贴 | B6: 12000 | C6: 3000 | D6: 半额：500 元/月 × 6 月；团队成员自剪为主
A7: 推广 | B7: 18000 | C7: 3000 | D7: 只做小额切片测试；回访达标后用到账收入追加
A8: 活动杂费 | B8: 4000 | C8: 2000 | D8: 按全年预算的一半
A9: 周边周转 | B9: 10500 | C9: 0 | D9: 延到下半年，改为预售回款后生产
A10: 支出小计 | B10: =SUM(B2:B9) | C10: =SUM(C2:C9)
A11: 预备金 | B11: 12500 | C11: =ROUND(C10*0.1,0) | D11: 推荐方案按支出小计的 10%
A12: 申请支持额 | B12: =B10+B11 | C12: =C10+C11 | D12: 推荐方案不把预测收入计作资金来源
A14: 首阶段预测收入（不计入资金来源） | C14: ='1 收入测算'!B6+'1 收入测算'!C6 | D14: Q1+Q2 打赏目标；若按期到账，可作额外缓冲
A15: 下半年（7–12 月）基准情景净现金 | C15: ='1 收入测算'!D6+'1 收入测算'!E6-26000-10500 | D15: Q3+Q4 收入 − 日常运营 26,000 − 周边履约 10,500；为正才进入扩张
A16: 说明 | D16: 原画与 Live2D 尚未付款，已全额计入；首阶段验收未通过时不进入下半年扩张，缺口不由本次申请覆盖
